{
    "build": {
        "beforeBuildCommand": "",
        "beforeDevCommand": "",
        "devPath": "../project",
        "distDir": "../project",
        "withGlobalTauri": true
    },
    "package": {
        "productName": "DonutMachineMZ",
        "version": "0.1.0"
    },
    "tauri": {
        "allowlist": {
            "path": {
                "all": true
            }
        },
        "bundle": {
            "active": true,
            "category": "Games",
            "copyright": "Copyright (C) Gotcha Gotcha Games Inc. / YOJI OJIMA 2020 / cursed_steven 2023",
            "deb": {
                "depends": []
            },
            "externalBin": [],
            "icon": [
                "icons/32x32.png",
                "icons/128x128.png",
                "icons/128x128@2x.png",
                "icons/icon.icns",
                "icons/icon.ico"
            ],
            "identifier": "com.donut-machine.dev",
            "longDescription": "",
            "macOS": {
                "entitlements": null,
                "exceptionDomain": "",
                "frameworks": [],
                "providerShortName": null,
                "signingIdentity": null,
                "minimumSystemVersion": "10.13"
            },
            "resources": [],
            "shortDescription": "",
            "targets": "all",
            "windows": {
                "certificateThumbprint": null,
                "digestAlgorithm": "sha256",
                "timestampUrl": ""
            }
        },
        "security": {
            "csp": null
        },
        "updater": {
            "active": false
        },
        "windows": [
            {
                "fullscreen": false,
                "height": 744,
                "resizable": false,
                "title": "Donut Machine",
                "width": 1280
            }
        ]
    }
}